<annotation>
	<folder>images</folder>
	<filename>IMG_20210912_122609.jpg</filename>
	<path>C:\Users\User\Desktop\Giana Tuna Salad Mexico 185g\images\IMG_20210912_122609.jpg</path>
	<source>
		<database>Unknown</database>
	</source>
	<size>
		<width>640</width>
		<height>480</height>
		<depth>3</depth>
	</size>
	<segmented>0</segmented>
	<object>
		<name>Giana Tuna Salad Mexico 185g</name>
		<pose>Unspecified</pose>
		<truncated>0</truncated>
		<difficult>0</difficult>
		<bndbox>
			<xmin>190</xmin>
			<ymin>128</ymin>
			<xmax>444</xmax>
			<ymax>333</ymax>
		</bndbox>
	</object>
</annotation>
